autoprocess/__init__.py
autoprocess/auto_analyse.py
autoprocess/auto_inputs.py
autoprocess/auto_integrate.py
autoprocess/auto_process.py
autoprocess/auto_report.py
autoprocess/auto_scale.py
autoprocess/auto_server.py
autoprocess/auto_signal.py
autoprocess/auto_strategy.py
autoprocess/auto_symmetry.py
autoprocess/errors.py
autoprocess/version.py
autoprocess/engine/__init__.py
autoprocess/engine/conversion.py
autoprocess/engine/indexing.py
autoprocess/engine/integration.py
autoprocess/engine/powder.py
autoprocess/engine/process.py
autoprocess/engine/reporting.py
autoprocess/engine/scaling.py
autoprocess/engine/solver.py
autoprocess/engine/spots.py
autoprocess/engine/strategy.py
autoprocess/engine/symmetry.py
autoprocess/parsers/__init__.py
autoprocess/parsers/best.py
autoprocess/parsers/distl.py
autoprocess/parsers/parser.py
autoprocess/parsers/phenix.py
autoprocess/parsers/pointless.py
autoprocess/parsers/xds.py
autoprocess/parsers/data/correct.yml
autoprocess/parsers/data/distl.yml
autoprocess/parsers/data/idxref.yml
autoprocess/parsers/data/integrate.yml
autoprocess/parsers/data/xdsstat.yml
autoprocess/parsers/data/xparm.yml
autoprocess/parsers/data/xplan.yml
autoprocess/parsers/data/xscale.yml
autoprocess/parsers/data/xtriage.yml
autoprocess/services/__init__.py
autoprocess/services/client.py
autoprocess/services/server.py
autoprocess/share/autoprocess.tac
autoprocess/share/report.html
autoprocess/share/report.js
autoprocess/share/report.min.css
autoprocess/share/report.min.js
autoprocess/share/report.scss
autoprocess/utils/__init__.py
autoprocess/utils/choices.py
autoprocess/utils/dataset.py
autoprocess/utils/diffsig.py
autoprocess/utils/ellipse.py
autoprocess/utils/fitio.py
autoprocess/utils/gnuplot.py
autoprocess/utils/log.py
autoprocess/utils/mdns.py
autoprocess/utils/misc.py
autoprocess/utils/options.py
autoprocess/utils/programs.py
autoprocess/utils/xdi.py
autoprocess/utils/xdsio.py
autoprocess/utils/xtal.py
autoprocess/utils/data/xtal_tables.jsonz
mx_autoprocess-2022.1.6.dist-info/LICENSE
mx_autoprocess-2022.1.6.dist-info/METADATA
mx_autoprocess-2022.1.6.dist-info/WHEEL
mx_autoprocess-2022.1.6.dist-info/top_level.txt
mx_autoprocess-2022.1.6.dist-info/RECORD
