Metadata-Version: 2.1
Name: mx-autoprocess
Version: 2022.1.6
Summary: AutoProcess
Home-page: https://github.com/michel4j/autoprocess
Author: Michel Fodje
Author-email: michel4j@gmail.com
License: MIT
Keywords: Automated Data Processing for MX
Platform: UNKNOWN
Classifier: Programming Language :: Python :: 3
Classifier: License :: OSI Approved :: MIT License
Classifier: Operating System :: OS Independent
License-File: LICENSE
Requires-Dist: cluster
Requires-Dist: scipy
Requires-Dist: Twisted
Requires-Dist: matplotlib
Requires-Dist: numpy
Requires-Dist: setuptools
Requires-Dist: msgpack-python
Requires-Dist: msgpack-numpy
Requires-Dist: mxio
Requires-Dist: pexpect
Requires-Dist: prettytable
Requires-Dist: progress
Requires-Dist: xvfbwrapper
Requires-Dist: PyYAML
Requires-Dist: zeroconf
Requires-Dist: zope.interface
Requires-Dist: scikit-image
Requires-Dist: zmq
Requires-Dist: importlib-metadata (~=1.0) ; python_version < "3.8"
